examples/vcs/uart_send/rtl/uart_send.v
//*****************************************************************************
//COPYRIGHT(c) South China University Of Techonology
//
//Module name  :uart_send
//File name    :uart_send.v
//
//Author       :TANG
//Email        :tangziming@whut.edu.cn
//Data         :2022.10.15
//Version      :1.0
/*Abstract

*/
/*Modify
    1.0:create the file
*/
//*****************************************************************************
module uart_send
#(
	parameter  CLK_FREQ = 50000000,
	parameter  UART_BPS = 9600
)
(
    input clk_i,                //global clock input
    input rst_n_i,              //global async reset input, active low
    
    input uart_en_i,            //uart send enable pulse signal input
    input [7 : 0] uart_din_i,   //uart send data input, sync with uart_en_i
	
	output uart_tx_busy_o,      //uart send busy flag output
    output uart_txd_o           //uart send physical output
);
localparam BPS_CNT  = CLK_FREQ/UART_BPS;

//uart_en_i rise edge detec
reg uart_en_i_d0; 
reg uart_en_i_d1;
wire en_flag;
always @(posedge clk_i or negedge rst_n_i) begin         
    if (!rst_n_i) begin
        uart_en_i_d0 <= 1'b0;                                  
        uart_en_i_d1 <= 1'b0;
    end                                                      
    else begin                                               
        uart_en_i_d0 <= uart_en_i;                               
        uart_en_i_d1 <= uart_en_i_d0;                            
    end
end
assign en_flag = (~uart_en_i_d1) & uart_en_i_d0;

//uart send start and stop
reg tx_flag;
reg [7 : 0] tx_data;
reg [3 : 0] tx_cnt;
reg [15 : 0] clk_cnt;
always @(posedge clk_i or negedge rst_n_i) begin         
    if (!rst_n_i) begin                                  
        tx_flag <= 1'b0;
        tx_data <= 8'd0;
    end 
    else if (en_flag) begin                
            tx_flag <= 1'b1;
            tx_data <= uart_din_i;
        end
        else 
        if ((tx_cnt == 4'd9)&&(clk_cnt == BPS_CNT - 1)) begin
            tx_flag <= 1'b0;
            tx_data <= 8'd0;
        end
        else begin
            tx_flag <= tx_flag;
            tx_data <= tx_data;
        end
end
assign uart_tx_busy_o = uart_en_i| uart_en_i_d0 | tx_flag;

//uart bps and tx bit number counter
always @(posedge clk_i or negedge rst_n_i) begin         
    if (!rst_n_i) begin                             
        clk_cnt <= 16'd0;                                  
        tx_cnt  <= 4'd0;
    end                                                      
    else if (tx_flag) begin
        if (clk_cnt < BPS_CNT - 1) begin
            clk_cnt <= clk_cnt + 1'b1;
            tx_cnt  <= tx_cnt;
        end
        else begin
            clk_cnt <= 16'd0;
            tx_cnt  <= tx_cnt + 1'b1;
        end
    end
    else begin
        clk_cnt <= 16'd0;
        tx_cnt  <= 4'd0;
    end
end

//put data bits to output port
reg uart_txd_o_r;
always @(posedge clk_i or negedge rst_n_i)begin        
    if (!rst_n_i)
        uart_txd_o_r <= 1'b1;        
    else if (tx_flag)
        case(tx_cnt)
            4'd0: uart_txd_o_r <= 1'b0;         //start bit
            4'd1: uart_txd_o_r <= tx_data[0];
            4'd2: uart_txd_o_r <= tx_data[1];
            4'd3: uart_txd_o_r <= tx_data[2];
            4'd4: uart_txd_o_r <= tx_data[3];
            4'd5: uart_txd_o_r <= tx_data[4];
            4'd6: uart_txd_o_r <= tx_data[5];
            4'd7: uart_txd_o_r <= tx_data[6];
            4'd8: uart_txd_o_r <= tx_data[7];
            4'd9: uart_txd_o_r <= 1'b1;         //stop bit
            default: ;
        endcase
    else 
        uart_txd_o_r <= 1'b1;
end
assign uart_txd_o = uart_txd_o_r;

endmodule

examples/vcs/uart_send/tb/uart_send_tb.v
//*****************************************************************************
//COPYRIGHT(c) South China University Of Techonology
//
//Module name  :uart_send_tb
//File name    :uart_send_tb.v
//
//Author       :TANG
//Email        :tangziming@whut.edu.cn
//Date         :2022/10/15

//Version      :1.0
/*Abstract

*/
//*****************************************************************************

`timescale  1ns / 1ps

module uart_send_tb;

// uart_send Parameters
parameter PERIOD    = 20      ;
parameter CLK_FREQ  = 50000000;
parameter UART_BPS  = 115200  ;

// uart_send Inputs
reg   clk_i                                = 0 ;
reg   rst_n_i                              = 0 ;
reg   uart_en_i                            = 0 ;
reg   [7 : 0]  uart_din_i                  = 0 ;

// uart_send Outputs
wire  uart_tx_busy_o                       ;
wire  uart_txd_o                           ;

//dump vcd file
initial begin
    $dumpfile("waveform.vcd");
    $dumpvars(0,uart_send_tb.uart_en_i,
                uart_send_tb.uart_tx_busy_o,
                uart_send_tb.uart_txd_o
                );
end

//dump fsbl
initial begin
    $fsdbDumpfile("waveform.fsdb");
    $fsdbDumpvars(0);
end

//Clock generate
initial
begin
    forever #(PERIOD/2)  clk_i=~clk_i;
end

//Reset generate
initial
begin
    #(PERIOD*2) rst_n_i  =  1;
end

//operations
reg [7:0] send_byte_cnt = 0;
always@(posedge clk_i or negedge rst_n_i)begin
    if(!rst_n_i)begin
        uart_en_i <= 1'b0;
        uart_din_i <= 8'h00;
    end
    else if(uart_tx_busy_o == 1'b0)begin
        case(send_byte_cnt)
            0:begin
                uart_en_i <= 1'b1;
                uart_din_i <= "H";
                send_byte_cnt <= send_byte_cnt + 8'd1;
            end
            1:begin
                uart_en_i <= 1'b1;
                uart_din_i <= "e";
                send_byte_cnt <= send_byte_cnt + 8'd1;
            end
            2:begin
                uart_en_i <= 1'b1;
                uart_din_i <= "l";
                send_byte_cnt <= send_byte_cnt + 8'd1;
            end
            3:begin
                uart_en_i <= 1'b1;
                uart_din_i <= "l";
                send_byte_cnt <= send_byte_cnt + 8'd1;
            end
            4:begin
                uart_en_i <= 1'b1;
                uart_din_i <= "o";
                send_byte_cnt <= send_byte_cnt + 8'd1;
            end
            5:begin
                uart_en_i <= 1'b1;
                uart_din_i <= " ";
                send_byte_cnt <= send_byte_cnt + 8'd1;
            end
            6:begin
                uart_en_i <= 1'b1;
                uart_din_i <= "W";
                send_byte_cnt <= send_byte_cnt + 8'd1;
            end
            7:begin
                uart_en_i <= 1'b1;
                uart_din_i <= "o";
                send_byte_cnt <= send_byte_cnt + 8'd1;
            end
            8:begin
                uart_en_i <= 1'b1;
                uart_din_i <= "r";
                send_byte_cnt <= send_byte_cnt + 8'd1;
            end
            9:begin
                uart_en_i <= 1'b1;
                uart_din_i <= "l";
                send_byte_cnt <= send_byte_cnt + 8'd1;
            end
            10:begin
                uart_en_i <= 1'b1;
                uart_din_i <= "d";
                send_byte_cnt <= send_byte_cnt + 8'd1;
            end
            11:begin
                uart_en_i <= 1'b1;
                uart_din_i <= "!";
                send_byte_cnt <= send_byte_cnt + 8'd1;
            end
            12:begin
                $finish;
            end

        endcase
    end
    else begin
        uart_en_i <= 1'b0;
    end
end

//Test top module
uart_send 
#(
    .CLK_FREQ ( CLK_FREQ ),
    .UART_BPS ( UART_BPS )
)
u_uart_send
(
    .clk_i                   ( clk_i                   ),
    .rst_n_i                 ( rst_n_i                 ),
    .uart_en_i               ( uart_en_i               ),
    .uart_din_i              ( uart_din_i      [7 : 0] ),

    .uart_tx_busy_o          ( uart_tx_busy_o          ),
    .uart_txd_o              ( uart_txd_o              )
);

endmodule

examples/modelsim/uart_send/waveform.vcd
$date
	Sat Oct 15 23:36:36 2022
$end
$version
	ModelSim Version 10.4
$end
$timescale
	1ps
$end

$scope module uart_send_tb $end
$var reg 1 ! uart_en_i $end
$var wire 1 " uart_tx_busy_o $end
$var wire 1 # uart_txd_o $end
$upscope $end
$enddefinitions $end
#0
$dumpvars
0!
0"
1#
$end
#50000
1!
1"
#70000
0!
#110000
0#
#34830000
1#
#43510000
0#
#60870000
1#
#69550000
0#
#78230000
1#
#86890000
0"
#86910000
1!
1"
#86930000
0!
#86970000
0#
#95650000
1#
#104330000
0#
#113010000
1#
#121690000
0#
#139050000
1#
#156410000
0#
#165090000
1#
#173750000
0"
#173770000
1!
1"
#173790000
0!
#173830000
0#
#199870000
1#
#217230000
0#
#225910000
1#
#243270000
0#
#251950000
1#
#260610000
0"
#260630000
1!
1"
#260650000
0!
#260690000
0#
#286730000
1#
#304090000
0#
#312770000
1#
#330130000
0#
#338810000
1#
#347470000
0"
#347490000
1!
1"
#347510000
0!
#347550000
0#
#356230000
1#
#390950000
0#
#399630000
1#
#416990000
0#
#425670000
1#
#434330000
0"
#434350000
1!
1"
#434370000
0!
#434410000
0#
#486490000
1#
#495170000
0#
#512530000
1#
#521190000
0"
#521210000
1!
1"
#521230000
0!
#521270000
0#
#529950000
1#
#555990000
0#
#564670000
1#
#573350000
0#
#582030000
1#
#590710000
0#
#599390000
1#
#608050000
0"
#608070000
1!
1"
#608090000
0!
#608130000
0#
#616810000
1#
#651530000
0#
#660210000
1#
#677570000
0#
#686250000
1#
#694910000
0"
#694930000
1!
1"
#694950000
0!
#694990000
0#
#712350000
1#
#721030000
0#
#738390000
1#
#764430000
0#
#773110000
1#
#781770000
0"
#781790000
1!
1"
#781810000
0!
#781850000
0#
#807890000
1#
#825250000
0#
#833930000
1#
#851290000
0#
#859970000
1#
#868630000
0"
#868650000
1!
1"
#868670000
0!
#868710000
0#
#894750000
1#
#903430000
0#
#920790000
1#
#938150000
0#
#946830000
1#
#955490000
0"
#955510000
1!
1"
#955530000
0!
#955570000
0#
#964250000
1#
#972930000
0#
#1007650000
1#
#1016330000
0#
#1033690000
1#
#1042350000
0"
