examples/vcs/vitual_logic_analyzer/tb/vitual_logic_decoder_tb.v
//*****************************************************************************
//COPYRIGHT(c) South China University Of Techonology
//
//Module name  :vitual_logic_decoder_tb
//File name    :vitual_logic_decoder_tb.v
//
//Author       :TANG
//Email        :tangziming@whut.edu.cn
//Date         :2022/10/15

//Version      :1.0
/*Abstract

*/
//*****************************************************************************

`timescale  1ns / 1ps

module vitual_logic_decoder_tb;

// vitual_logic_analyzer Parameters
parameter PERIOD         = 10        ;
parameter SAMP_CLK_FREQ  = 100_000_000;
parameter SAMP_CHANNELS  = 8         ;

// vitual_logic_analyzer Inputs
reg   clk_i                                = 0 ;
reg   [SAMP_CHANNELS-1 : 0]  data_i        = 0 ;

// vitual_logic_analyzer Outputs

initial begin
    $dumpfile("waveform.vcd");
    $dumpvars(0, vitual_logic_decoder_tb.clk_i, vitual_logic_decoder_tb.data_i);
end

//dump fsbl
initial begin
    $fsdbDumpfile("waveform.fsdb");
    $fsdbDumpvars(0);
end

//Clock generate
initial
begin
    forever #(PERIOD/2)  clk_i=~clk_i;
end

always@(posedge clk_i)begin
    data_i <= data_i + 8'd1;
end

//operations
initial
begin
    #6000
    $finish;
end

endmodule

examples/modelsim/vitual_logic_decoder/waveform.vcd
$date
	Sat Oct 15 23:42:07 2022
$end
$version
	ModelSim Version 10.4
$end
$timescale
	1ps
$end

$scope module vitual_logic_decoder_tb $end
$var reg 1 ! clk_i $end
$var reg 8 " data_i [7:0] $end
$upscope $end
$enddefinitions $end
#0
$dumpvars
0!
b0 "
$end
#5000
1!
b1 "
#10000
0!
#15000
1!
b10 "
#20000
0!
#25000
1!
b11 "
#30000
0!
#35000
1!
b100 "
#40000
0!
#45000
1!
b101 "
#50000
0!
#55000
1!
b110 "
#60000
0!
#65000
1!
b111 "
#70000
0!
#75000
1!
b1000 "
#80000
0!
#85000
1!
b1001 "
#90000
0!
#95000
1!
b1010 "
#100000
0!
#105000
1!
b1011 "
#110000
0!
#115000
1!
b1100 "
#120000
0!
#125000
1!
b1101 "
#130000
0!
#135000
1!
b1110 "
#140000
0!
#145000
1!
b1111 "
#150000
0!
#155000
1!
b10000 "
#160000
0!
#165000
1!
b10001 "
#170000
0!
#175000
1!
b10010 "
#180000
0!
#185000
1!
b10011 "
#190000
0!
#195000
1!
b10100 "
#200000
0!
#205000
1!
b10101 "
#210000
0!
#215000
1!
b10110 "
#220000
0!
#225000
1!
b10111 "
#230000
0!
#235000
1!
b11000 "
#240000
0!
#245000
1!
b11001 "
#250000
0!
#255000
1!
b11010 "
#260000
0!
#265000
1!
b11011 "
#270000
0!
#275000
1!
b11100 "
#280000
0!
#285000
1!
b11101 "
#290000
0!
#295000
1!
b11110 "
#300000
0!
#305000
1!
b11111 "
#310000
0!
#315000
1!
b100000 "
#320000
0!
#325000
1!
b100001 "
#330000
0!
#335000
1!
b100010 "
#340000
0!
#345000
1!
b100011 "
#350000
0!
#355000
1!
b100100 "
#360000
0!
#365000
1!
b100101 "
#370000
0!
#375000
1!
b100110 "
#380000
0!
#385000
1!
b100111 "
#390000
0!
#395000
1!
b101000 "
#400000
0!
#405000
1!
b101001 "
#410000
0!
#415000
1!
b101010 "
#420000
0!
#425000
1!
b101011 "
#430000
0!
#435000
1!
b101100 "
#440000
0!
#445000
1!
b101101 "
#450000
0!
#455000
1!
b101110 "
#460000
0!
#465000
1!
b101111 "
#470000
0!
#475000
1!
b110000 "
#480000
0!
#485000
1!
b110001 "
#490000
0!
#495000
1!
b110010 "
#500000
0!
#505000
1!
b110011 "
#510000
0!
#515000
1!
b110100 "
#520000
0!
#525000
1!
b110101 "
#530000
0!
#535000
1!
b110110 "
#540000
0!
#545000
1!
b110111 "
#550000
0!
#555000
1!
b111000 "
#560000
0!
#565000
1!
b111001 "
#570000
0!
#575000
1!
b111010 "
#580000
0!
#585000
1!
b111011 "
#590000
0!
#595000
1!
b111100 "
#600000
0!
#605000
1!
b111101 "
#610000
0!
#615000
1!
b111110 "
#620000
0!
#625000
1!
b111111 "
#630000
0!
#635000
1!
b1000000 "
#640000
0!
#645000
1!
b1000001 "
#650000
0!
#655000
1!
b1000010 "
#660000
0!
#665000
1!
b1000011 "
#670000
0!
#675000
1!
b1000100 "
#680000
0!
#685000
1!
b1000101 "
#690000
0!
#695000
1!
b1000110 "
#700000
0!
#705000
1!
b1000111 "
#710000
0!
#715000
1!
b1001000 "
#720000
0!
#725000
1!
b1001001 "
#730000
0!
#735000
1!
b1001010 "
#740000
0!
#745000
1!
b1001011 "
#750000
0!
#755000
1!
b1001100 "
#760000
0!
#765000
1!
b1001101 "
#770000
0!
#775000
1!
b1001110 "
#780000
0!
#785000
1!
b1001111 "
#790000
0!
#795000
1!
b1010000 "
#800000
0!
#805000
1!
b1010001 "
#810000
0!
#815000
1!
b1010010 "
#820000
0!
#825000
1!
b1010011 "
#830000
0!
#835000
1!
b1010100 "
#840000
0!
#845000
1!
b1010101 "
#850000
0!
#855000
1!
b1010110 "
#860000
0!
#865000
1!
b1010111 "
#870000
0!
#875000
1!
b1011000 "
#880000
0!
#885000
1!
b1011001 "
#890000
0!
#895000
1!
b1011010 "
#900000
0!
#905000
1!
b1011011 "
#910000
0!
#915000
1!
b1011100 "
#920000
0!
#925000
1!
b1011101 "
#930000
0!
#935000
1!
b1011110 "
#940000
0!
#945000
1!
b1011111 "
#950000
0!
#955000
1!
b1100000 "
#960000
0!
#965000
1!
b1100001 "
#970000
0!
#975000
1!
b1100010 "
#980000
0!
#985000
1!
b1100011 "
#990000
0!
#995000
1!
b1100100 "
#1000000
0!
#1005000
1!
b1100101 "
#1010000
0!
#1015000
1!
b1100110 "
#1020000
0!
#1025000
1!
b1100111 "
#1030000
0!
#1035000
1!
b1101000 "
#1040000
0!
#1045000
1!
b1101001 "
#1050000
0!
#1055000
1!
b1101010 "
#1060000
0!
#1065000
1!
b1101011 "
#1070000
0!
#1075000
1!
b1101100 "
#1080000
0!
#1085000
1!
b1101101 "
#1090000
0!
#1095000
1!
b1101110 "
#1100000
0!
#1105000
1!
b1101111 "
#1110000
0!
#1115000
1!
b1110000 "
#1120000
0!
#1125000
1!
b1110001 "
#1130000
0!
#1135000
1!
b1110010 "
#1140000
0!
#1145000
1!
b1110011 "
#1150000
0!
#1155000
1!
b1110100 "
#1160000
0!
#1165000
1!
b1110101 "
#1170000
0!
#1175000
1!
b1110110 "
#1180000
0!
#1185000
1!
b1110111 "
#1190000
0!
#1195000
1!
b1111000 "
#1200000
0!
#1205000
1!
b1111001 "
#1210000
0!
#1215000
1!
b1111010 "
#1220000
0!
#1225000
1!
b1111011 "
#1230000
0!
#1235000
1!
b1111100 "
#1240000
0!
#1245000
1!
b1111101 "
#1250000
0!
#1255000
1!
b1111110 "
#1260000
0!
#1265000
1!
b1111111 "
#1270000
0!
#1275000
1!
b10000000 "
#1280000
0!
#1285000
1!
b10000001 "
#1290000
0!
#1295000
1!
b10000010 "
#1300000
0!
#1305000
1!
b10000011 "
#1310000
0!
#1315000
1!
b10000100 "
#1320000
0!
#1325000
1!
b10000101 "
#1330000
0!
#1335000
1!
b10000110 "
#1340000
0!
#1345000
1!
b10000111 "
#1350000
0!
#1355000
1!
b10001000 "
#1360000
0!
#1365000
1!
b10001001 "
#1370000
0!
#1375000
1!
b10001010 "
#1380000
0!
#1385000
1!
b10001011 "
#1390000
0!
#1395000
1!
b10001100 "
#1400000
0!
#1405000
1!
b10001101 "
#1410000
0!
#1415000
1!
b10001110 "
#1420000
0!
#1425000
1!
b10001111 "
#1430000
0!
#1435000
1!
b10010000 "
#1440000
0!
#1445000
1!
b10010001 "
#1450000
0!
#1455000
1!
b10010010 "
#1460000
0!
#1465000
1!
b10010011 "
#1470000
0!
#1475000
1!
b10010100 "
#1480000
0!
#1485000
1!
b10010101 "
#1490000
0!
#1495000
1!
b10010110 "
#1500000
0!
#1505000
1!
b10010111 "
#1510000
0!
#1515000
1!
b10011000 "
#1520000
0!
#1525000
1!
b10011001 "
#1530000
0!
#1535000
1!
b10011010 "
#1540000
0!
#1545000
1!
b10011011 "
#1550000
0!
#1555000
1!
b10011100 "
#1560000
0!
#1565000
1!
b10011101 "
#1570000
0!
#1575000
1!
b10011110 "
#1580000
0!
#1585000
1!
b10011111 "
#1590000
0!
#1595000
1!
b10100000 "
#1600000
0!
#1605000
1!
b10100001 "
#1610000
0!
#1615000
1!
b10100010 "
#1620000
0!
#1625000
1!
b10100011 "
#1630000
0!
#1635000
1!
b10100100 "
#1640000
0!
#1645000
1!
b10100101 "
#1650000
0!
#1655000
1!
b10100110 "
#1660000
0!
#1665000
1!
b10100111 "
#1670000
0!
#1675000
1!
b10101000 "
#1680000
0!
#1685000
1!
b10101001 "
#1690000
0!
#1695000
1!
b10101010 "
#1700000
0!
#1705000
1!
b10101011 "
#1710000
0!
#1715000
1!
b10101100 "
#1720000
0!
#1725000
1!
b10101101 "
#1730000
0!
#1735000
1!
b10101110 "
#1740000
0!
#1745000
1!
b10101111 "
#1750000
0!
#1755000
1!
b10110000 "
#1760000
0!
#1765000
1!
b10110001 "
#1770000
0!
#1775000
1!
b10110010 "
#1780000
0!
#1785000
1!
b10110011 "
#1790000
0!
#1795000
1!
b10110100 "
#1800000
0!
#1805000
1!
b10110101 "
#1810000
0!
#1815000
1!
b10110110 "
#1820000
0!
#1825000
1!
b10110111 "
#1830000
0!
#1835000
1!
b10111000 "
#1840000
0!
#1845000
1!
b10111001 "
#1850000
0!
#1855000
1!
b10111010 "
#1860000
0!
#1865000
1!
b10111011 "
#1870000
0!
#1875000
1!
b10111100 "
#1880000
0!
#1885000
1!
b10111101 "
#1890000
0!
#1895000
1!
b10111110 "
#1900000
0!
#1905000
1!
b10111111 "
#1910000
0!
#1915000
1!
b11000000 "
#1920000
0!
#1925000
1!
b11000001 "
#1930000
0!
#1935000
1!
b11000010 "
#1940000
0!
#1945000
1!
b11000011 "
#1950000
0!
#1955000
1!
b11000100 "
#1960000
0!
#1965000
1!
b11000101 "
#1970000
0!
#1975000
1!
b11000110 "
#1980000
0!
#1985000
1!
b11000111 "
#1990000
0!
#1995000
1!
b11001000 "
#2000000
0!
#2005000
1!
b11001001 "
#2010000
0!
#2015000
1!
b11001010 "
#2020000
0!
#2025000
1!
b11001011 "
#2030000
0!
#2035000
1!
b11001100 "
#2040000
0!
#2045000
1!
b11001101 "
#2050000
0!
#2055000
1!
b11001110 "
#2060000
0!
#2065000
1!
b11001111 "
#2070000
0!
#2075000
1!
b11010000 "
#2080000
0!
#2085000
1!
b11010001 "
#2090000
0!
#2095000
1!
b11010010 "
#2100000
0!
#2105000
1!
b11010011 "
#2110000
0!
#2115000
1!
b11010100 "
#2120000
0!
#2125000
1!
b11010101 "
#2130000
0!
#2135000
1!
b11010110 "
#2140000
0!
#2145000
1!
b11010111 "
#2150000
0!
#2155000
1!
b11011000 "
#2160000
0!
#2165000
1!
b11011001 "
#2170000
0!
#2175000
1!
b11011010 "
#2180000
0!
#2185000
1!
b11011011 "
#2190000
0!
#2195000
1!
b11011100 "
#2200000
0!
#2205000
1!
b11011101 "
#2210000
0!
#2215000
1!
b11011110 "
#2220000
0!
#2225000
1!
b11011111 "
#2230000
0!
#2235000
1!
b11100000 "
#2240000
0!
#2245000
1!
b11100001 "
#2250000
0!
#2255000
1!
b11100010 "
#2260000
0!
#2265000
1!
b11100011 "
#2270000
0!
#2275000
1!
b11100100 "
#2280000
0!
#2285000
1!
b11100101 "
#2290000
0!
#2295000
1!
b11100110 "
#2300000
0!
#2305000
1!
b11100111 "
#2310000
0!
#2315000
1!
b11101000 "
#2320000
0!
#2325000
1!
b11101001 "
#2330000
0!
#2335000
1!
b11101010 "
#2340000
0!
#2345000
1!
b11101011 "
#2350000
0!
#2355000
1!
b11101100 "
#2360000
0!
#2365000
1!
b11101101 "
#2370000
0!
#2375000
1!
b11101110 "
#2380000
0!
#2385000
1!
b11101111 "
#2390000
0!
#2395000
1!
b11110000 "
#2400000
0!
#2405000
1!
b11110001 "
#2410000
0!
#2415000
1!
b11110010 "
#2420000
0!
#2425000
1!
b11110011 "
#2430000
0!
#2435000
1!
b11110100 "
#2440000
0!
#2445000
1!
b11110101 "
#2450000
0!
#2455000
1!
b11110110 "
#2460000
0!
#2465000
1!
b11110111 "
#2470000
0!
#2475000
1!
b11111000 "
#2480000
0!
#2485000
1!
b11111001 "
#2490000
0!
#2495000
1!
b11111010 "
#2500000
0!
#2505000
1!
b11111011 "
#2510000
0!
#2515000
1!
b11111100 "
#2520000
0!
#2525000
1!
b11111101 "
#2530000
0!
#2535000
1!
b11111110 "
#2540000
0!
#2545000
1!
b11111111 "
#2550000
0!
#2555000
1!
b0 "
#2560000
0!
#2565000
1!
b1 "
#2570000
0!
#2575000
1!
b10 "
#2580000
0!
#2585000
1!
b11 "
#2590000
0!
#2595000
1!
b100 "
#2600000
0!
#2605000
1!
b101 "
#2610000
0!
#2615000
1!
b110 "
#2620000
0!
#2625000
1!
b111 "
#2630000
0!
#2635000
1!
b1000 "
#2640000
0!
#2645000
1!
b1001 "
#2650000
0!
#2655000
1!
b1010 "
#2660000
0!
#2665000
1!
b1011 "
#2670000
0!
#2675000
1!
b1100 "
#2680000
0!
#2685000
1!
b1101 "
#2690000
0!
#2695000
1!
b1110 "
#2700000
0!
#2705000
1!
b1111 "
#2710000
0!
#2715000
1!
b10000 "
#2720000
0!
#2725000
1!
b10001 "
#2730000
0!
#2735000
1!
b10010 "
#2740000
0!
#2745000
1!
b10011 "
#2750000
0!
#2755000
1!
b10100 "
#2760000
0!
#2765000
1!
b10101 "
#2770000
0!
#2775000
1!
b10110 "
#2780000
0!
#2785000
1!
b10111 "
#2790000
0!
#2795000
1!
b11000 "
#2800000
0!
#2805000
1!
b11001 "
#2810000
0!
#2815000
1!
b11010 "
#2820000
0!
#2825000
1!
b11011 "
#2830000
0!
#2835000
1!
b11100 "
#2840000
0!
#2845000
1!
b11101 "
#2850000
0!
#2855000
1!
b11110 "
#2860000
0!
#2865000
1!
b11111 "
#2870000
0!
#2875000
1!
b100000 "
#2880000
0!
#2885000
1!
b100001 "
#2890000
0!
#2895000
1!
b100010 "
#2900000
0!
#2905000
1!
b100011 "
#2910000
0!
#2915000
1!
b100100 "
#2920000
0!
#2925000
1!
b100101 "
#2930000
0!
#2935000
1!
b100110 "
#2940000
0!
#2945000
1!
b100111 "
#2950000
0!
#2955000
1!
b101000 "
#2960000
0!
#2965000
1!
b101001 "
#2970000
0!
#2975000
1!
b101010 "
#2980000
0!
#2985000
1!
b101011 "
#2990000
0!
#2995000
1!
b101100 "
#3000000
0!
#3005000
1!
b101101 "
#3010000
0!
#3015000
1!
b101110 "
#3020000
0!
#3025000
1!
b101111 "
#3030000
0!
#3035000
1!
b110000 "
#3040000
0!
#3045000
1!
b110001 "
#3050000
0!
#3055000
1!
b110010 "
#3060000
0!
#3065000
1!
b110011 "
#3070000
0!
#3075000
1!
b110100 "
#3080000
0!
#3085000
1!
b110101 "
#3090000
0!
#3095000
1!
b110110 "
#3100000
0!
#3105000
1!
b110111 "
#3110000
0!
#3115000
1!
b111000 "
#3120000
0!
#3125000
1!
b111001 "
#3130000
0!
#3135000
1!
b111010 "
#3140000
0!
#3145000
1!
b111011 "
#3150000
0!
#3155000
1!
b111100 "
#3160000
0!
#3165000
1!
b111101 "
#3170000
0!
#3175000
1!
b111110 "
#3180000
0!
#3185000
1!
b111111 "
#3190000
0!
#3195000
1!
b1000000 "
#3200000
0!
#3205000
1!
b1000001 "
#3210000
0!
#3215000
1!
b1000010 "
#3220000
0!
#3225000
1!
b1000011 "
#3230000
0!
#3235000
1!
b1000100 "
#3240000
0!
#3245000
1!
b1000101 "
#3250000
0!
#3255000
1!
b1000110 "
#3260000
0!
#3265000
1!
b1000111 "
#3270000
0!
#3275000
1!
b1001000 "
#3280000
0!
#3285000
1!
b1001001 "
#3290000
0!
#3295000
1!
b1001010 "
#3300000
0!
#3305000
1!
b1001011 "
#3310000
0!
#3315000
1!
b1001100 "
#3320000
0!
#3325000
1!
b1001101 "
#3330000
0!
#3335000
1!
b1001110 "
#3340000
0!
#3345000
1!
b1001111 "
#3350000
0!
#3355000
1!
b1010000 "
#3360000
0!
#3365000
1!
b1010001 "
#3370000
0!
#3375000
1!
b1010010 "
#3380000
0!
#3385000
1!
b1010011 "
#3390000
0!
#3395000
1!
b1010100 "
#3400000
0!
#3405000
1!
b1010101 "
#3410000
0!
#3415000
1!
b1010110 "
#3420000
0!
#3425000
1!
b1010111 "
#3430000
0!
#3435000
1!
b1011000 "
#3440000
0!
#3445000
1!
b1011001 "
#3450000
0!
#3455000
1!
b1011010 "
#3460000
0!
#3465000
1!
b1011011 "
#3470000
0!
#3475000
1!
b1011100 "
#3480000
0!
#3485000
1!
b1011101 "
#3490000
0!
#3495000
1!
b1011110 "
#3500000
0!
#3505000
1!
b1011111 "
#3510000
0!
#3515000
1!
b1100000 "
#3520000
0!
#3525000
1!
b1100001 "
#3530000
0!
#3535000
1!
b1100010 "
#3540000
0!
#3545000
1!
b1100011 "
#3550000
0!
#3555000
1!
b1100100 "
#3560000
0!
#3565000
1!
b1100101 "
#3570000
0!
#3575000
1!
b1100110 "
#3580000
0!
#3585000
1!
b1100111 "
#3590000
0!
#3595000
1!
b1101000 "
#3600000
0!
#3605000
1!
b1101001 "
#3610000
0!
#3615000
1!
b1101010 "
#3620000
0!
#3625000
1!
b1101011 "
#3630000
0!
#3635000
1!
b1101100 "
#3640000
0!
#3645000
1!
b1101101 "
#3650000
0!
#3655000
1!
b1101110 "
#3660000
0!
#3665000
1!
b1101111 "
#3670000
0!
#3675000
1!
b1110000 "
#3680000
0!
#3685000
1!
b1110001 "
#3690000
0!
#3695000
1!
b1110010 "
#3700000
0!
#3705000
1!
b1110011 "
#3710000
0!
#3715000
1!
b1110100 "
#3720000
0!
#3725000
1!
b1110101 "
#3730000
0!
#3735000
1!
b1110110 "
#3740000
0!
#3745000
1!
b1110111 "
#3750000
0!
#3755000
1!
b1111000 "
#3760000
0!
#3765000
1!
b1111001 "
#3770000
0!
#3775000
1!
b1111010 "
#3780000
0!
#3785000
1!
b1111011 "
#3790000
0!
#3795000
1!
b1111100 "
#3800000
0!
#3805000
1!
b1111101 "
#3810000
0!
#3815000
1!
b1111110 "
#3820000
0!
#3825000
1!
b1111111 "
#3830000
0!
#3835000
1!
b10000000 "
#3840000
0!
#3845000
1!
b10000001 "
#3850000
0!
#3855000
1!
b10000010 "
#3860000
0!
#3865000
1!
b10000011 "
#3870000
0!
#3875000
1!
b10000100 "
#3880000
0!
#3885000
1!
b10000101 "
#3890000
0!
#3895000
1!
b10000110 "
#3900000
0!
#3905000
1!
b10000111 "
#3910000
0!
#3915000
1!
b10001000 "
#3920000
0!
#3925000
1!
b10001001 "
#3930000
0!
#3935000
1!
b10001010 "
#3940000
0!
#3945000
1!
b10001011 "
#3950000
0!
#3955000
1!
b10001100 "
#3960000
0!
#3965000
1!
b10001101 "
#3970000
0!
#3975000
1!
b10001110 "
#3980000
0!
#3985000
1!
b10001111 "
#3990000
0!
#3995000
1!
b10010000 "
#4000000
0!
#4005000
1!
b10010001 "
#4010000
0!
#4015000
1!
b10010010 "
#4020000
0!
#4025000
1!
b10010011 "
#4030000
0!
#4035000
1!
b10010100 "
#4040000
0!
#4045000
1!
b10010101 "
#4050000
0!
#4055000
1!
b10010110 "
#4060000
0!
#4065000
1!
b10010111 "
#4070000
0!
#4075000
1!
b10011000 "
#4080000
0!
#4085000
1!
b10011001 "
#4090000
0!
#4095000
1!
b10011010 "
#4100000
0!
#4105000
1!
b10011011 "
#4110000
0!
#4115000
1!
b10011100 "
#4120000
0!
#4125000
1!
b10011101 "
#4130000
0!
#4135000
1!
b10011110 "
#4140000
0!
#4145000
1!
b10011111 "
#4150000
0!
#4155000
1!
b10100000 "
#4160000
0!
#4165000
1!
b10100001 "
#4170000
0!
#4175000
1!
b10100010 "
#4180000
0!
#4185000
1!
b10100011 "
#4190000
0!
#4195000
1!
b10100100 "
#4200000
0!
#4205000
1!
b10100101 "
#4210000
0!
#4215000
1!
b10100110 "
#4220000
0!
#4225000
1!
b10100111 "
#4230000
0!
#4235000
1!
b10101000 "
#4240000
0!
#4245000
1!
b10101001 "
#4250000
0!
#4255000
1!
b10101010 "
#4260000
0!
#4265000
1!
b10101011 "
#4270000
0!
#4275000
1!
b10101100 "
#4280000
0!
#4285000
1!
b10101101 "
#4290000
0!
#4295000
1!
b10101110 "
#4300000
0!
#4305000
1!
b10101111 "
#4310000
0!
#4315000
1!
b10110000 "
#4320000
0!
#4325000
1!
b10110001 "
#4330000
0!
#4335000
1!
b10110010 "
#4340000
0!
#4345000
1!
b10110011 "
#4350000
0!
#4355000
1!
b10110100 "
#4360000
0!
#4365000
1!
b10110101 "
#4370000
0!
#4375000
1!
b10110110 "
#4380000
0!
#4385000
1!
b10110111 "
#4390000
0!
#4395000
1!
b10111000 "
#4400000
0!
#4405000
1!
b10111001 "
#4410000
0!
#4415000
1!
b10111010 "
#4420000
0!
#4425000
1!
b10111011 "
#4430000
0!
#4435000
1!
b10111100 "
#4440000
0!
#4445000
1!
b10111101 "
#4450000
0!
#4455000
1!
b10111110 "
#4460000
0!
#4465000
1!
b10111111 "
#4470000
0!
#4475000
1!
b11000000 "
#4480000
0!
#4485000
1!
b11000001 "
#4490000
0!
#4495000
1!
b11000010 "
#4500000
0!
#4505000
1!
b11000011 "
#4510000
0!
#4515000
1!
b11000100 "
#4520000
0!
#4525000
1!
b11000101 "
#4530000
0!
#4535000
1!
b11000110 "
#4540000
0!
#4545000
1!
b11000111 "
#4550000
0!
#4555000
1!
b11001000 "
#4560000
0!
#4565000
1!
b11001001 "
#4570000
0!
#4575000
1!
b11001010 "
#4580000
0!
#4585000
1!
b11001011 "
#4590000
0!
#4595000
1!
b11001100 "
#4600000
0!
#4605000
1!
b11001101 "
#4610000
0!
#4615000
1!
b11001110 "
#4620000
0!
#4625000
1!
b11001111 "
#4630000
0!
#4635000
1!
b11010000 "
#4640000
0!
#4645000
1!
b11010001 "
#4650000
0!
#4655000
1!
b11010010 "
#4660000
0!
#4665000
1!
b11010011 "
#4670000
0!
#4675000
1!
b11010100 "
#4680000
0!
#4685000
1!
b11010101 "
#4690000
0!
#4695000
1!
b11010110 "
#4700000
0!
#4705000
1!
b11010111 "
#4710000
0!
#4715000
1!
b11011000 "
#4720000
0!
#4725000
1!
b11011001 "
#4730000
0!
#4735000
1!
b11011010 "
#4740000
0!
#4745000
1!
b11011011 "
#4750000
0!
#4755000
1!
b11011100 "
#4760000
0!
#4765000
1!
b11011101 "
#4770000
0!
#4775000
1!
b11011110 "
#4780000
0!
#4785000
1!
b11011111 "
#4790000
0!
#4795000
1!
b11100000 "
#4800000
0!
#4805000
1!
b11100001 "
#4810000
0!
#4815000
1!
b11100010 "
#4820000
0!
#4825000
1!
b11100011 "
#4830000
0!
#4835000
1!
b11100100 "
#4840000
0!
#4845000
1!
b11100101 "
#4850000
0!
#4855000
1!
b11100110 "
#4860000
0!
#4865000
1!
b11100111 "
#4870000
0!
#4875000
1!
b11101000 "
#4880000
0!
#4885000
1!
b11101001 "
#4890000
0!
#4895000
1!
b11101010 "
#4900000
0!
#4905000
1!
b11101011 "
#4910000
0!
#4915000
1!
b11101100 "
#4920000
0!
#4925000
1!
b11101101 "
#4930000
0!
#4935000
1!
b11101110 "
#4940000
0!
#4945000
1!
b11101111 "
#4950000
0!
#4955000
1!
b11110000 "
#4960000
0!
#4965000
1!
b11110001 "
#4970000
0!
#4975000
1!
b11110010 "
#4980000
0!
#4985000
1!
b11110011 "
#4990000
0!
#4995000
1!
b11110100 "
#5000000
0!
#5005000
1!
b11110101 "
#5010000
0!
#5015000
1!
b11110110 "
#5020000
0!
#5025000
1!
b11110111 "
#5030000
0!
#5035000
1!
b11111000 "
#5040000
0!
#5045000
1!
b11111001 "
#5050000
0!
#5055000
1!
b11111010 "
#5060000
0!
#5065000
1!
b11111011 "
#5070000
0!
#5075000
1!
b11111100 "
#5080000
0!
#5085000
1!
b11111101 "
#5090000
0!
#5095000
1!
b11111110 "
#5100000
0!
#5105000
1!
b11111111 "
#5110000
0!
#5115000
1!
b0 "
#5120000
0!
#5125000
1!
b1 "
#5130000
0!
#5135000
1!
b10 "
#5140000
0!
#5145000
1!
b11 "
#5150000
0!
#5155000
1!
b100 "
#5160000
0!
#5165000
1!
b101 "
#5170000
0!
#5175000
1!
b110 "
#5180000
0!
#5185000
1!
b111 "
#5190000
0!
#5195000
1!
b1000 "
#5200000
0!
#5205000
1!
b1001 "
#5210000
0!
#5215000
1!
b1010 "
#5220000
0!
#5225000
1!
b1011 "
#5230000
0!
#5235000
1!
b1100 "
#5240000
0!
#5245000
1!
b1101 "
#5250000
0!
#5255000
1!
b1110 "
#5260000
0!
#5265000
1!
b1111 "
#5270000
0!
#5275000
1!
b10000 "
#5280000
0!
#5285000
1!
b10001 "
#5290000
0!
#5295000
1!
b10010 "
#5300000
0!
#5305000
1!
b10011 "
#5310000
0!
#5315000
1!
b10100 "
#5320000
0!
#5325000
1!
b10101 "
#5330000
0!
#5335000
1!
b10110 "
#5340000
0!
#5345000
1!
b10111 "
#5350000
0!
#5355000
1!
b11000 "
#5360000
0!
#5365000
1!
b11001 "
#5370000
0!
#5375000
1!
b11010 "
#5380000
0!
#5385000
1!
b11011 "
#5390000
0!
#5395000
1!
b11100 "
#5400000
0!
#5405000
1!
b11101 "
#5410000
0!
#5415000
1!
b11110 "
#5420000
0!
#5425000
1!
b11111 "
#5430000
0!
#5435000
1!
b100000 "
#5440000
0!
#5445000
1!
b100001 "
#5450000
0!
#5455000
1!
b100010 "
#5460000
0!
#5465000
1!
b100011 "
#5470000
0!
#5475000
1!
b100100 "
#5480000
0!
#5485000
1!
b100101 "
#5490000
0!
#5495000
1!
b100110 "
#5500000
0!
#5505000
1!
b100111 "
#5510000
0!
#5515000
1!
b101000 "
#5520000
0!
#5525000
1!
b101001 "
#5530000
0!
#5535000
1!
b101010 "
#5540000
0!
#5545000
1!
b101011 "
#5550000
0!
#5555000
1!
b101100 "
#5560000
0!
#5565000
1!
b101101 "
#5570000
0!
#5575000
1!
b101110 "
#5580000
0!
#5585000
1!
b101111 "
#5590000
0!
#5595000
1!
b110000 "
#5600000
0!
#5605000
1!
b110001 "
#5610000
0!
#5615000
1!
b110010 "
#5620000
0!
#5625000
1!
b110011 "
#5630000
0!
#5635000
1!
b110100 "
#5640000
0!
#5645000
1!
b110101 "
#5650000
0!
#5655000
1!
b110110 "
#5660000
0!
#5665000
1!
b110111 "
#5670000
0!
#5675000
1!
b111000 "
#5680000
0!
#5685000
1!
b111001 "
#5690000
0!
#5695000
1!
b111010 "
#5700000
0!
#5705000
1!
b111011 "
#5710000
0!
#5715000
1!
b111100 "
#5720000
0!
#5725000
1!
b111101 "
#5730000
0!
#5735000
1!
b111110 "
#5740000
0!
#5745000
1!
b111111 "
#5750000
0!
#5755000
1!
b1000000 "
#5760000
0!
#5765000
1!
b1000001 "
#5770000
0!
#5775000
1!
b1000010 "
#5780000
0!
#5785000
1!
b1000011 "
#5790000
0!
#5795000
1!
b1000100 "
#5800000
0!
#5805000
1!
b1000101 "
#5810000
0!
#5815000
1!
b1000110 "
#5820000
0!
#5825000
1!
b1000111 "
#5830000
0!
#5835000
1!
b1001000 "
#5840000
0!
#5845000
1!
b1001001 "
#5850000
0!
#5855000
1!
b1001010 "
#5860000
0!
#5865000
1!
b1001011 "
#5870000
0!
#5875000
1!
b10